tradernet_client/__init__.py
tradernet_client/client.py
tradernet_client/schemas.py
tradernet_client/utils.py
tradernet_client-0.7.0.dist-info/WHEEL
tradernet_client-0.7.0.dist-info/METADATA
tradernet_client-0.7.0.dist-info/RECORD
